hmd_cli_bartleby/__init__.py
hmd_cli_bartleby/controller.py
hmd_cli_bartleby/hmd_cli_bartleby.py
hmd_cli_bartleby-1.0.44.dist-info/METADATA
hmd_cli_bartleby-1.0.44.dist-info/WHEEL
hmd_cli_bartleby-1.0.44.dist-info/top_level.txt
hmd_cli_bartleby-1.0.44.dist-info/RECORD
